COPYING
COPYING.lesser
MANIFEST.in
NOTICE
README.md
pyproject.toml
requirements.txt
setup.py
compiler/__init__.py
compiler/api/__init__.py
compiler/api/compiler.py
compiler/api/source/auth_key.tl
compiler/api/source/main_api.tl
compiler/api/source/sys_msgs.tl
compiler/api/template/combinator.txt
compiler/api/template/type.txt
compiler/docs/__init__.py
compiler/docs/compiler.py
compiler/docs/template/page.txt
compiler/docs/template/toctree.txt
compiler/errors/__init__.py
compiler/errors/compiler.py
compiler/errors/sort.py
compiler/errors/source/303_SEE_OTHER.tsv
compiler/errors/source/400_BAD_REQUEST.tsv
compiler/errors/source/401_UNAUTHORIZED.tsv
compiler/errors/source/403_FORBIDDEN.tsv
compiler/errors/source/406_NOT_ACCEPTABLE.tsv
compiler/errors/source/420_FLOOD.tsv
compiler/errors/source/500_INTERNAL_SERVER_ERROR.tsv
compiler/errors/source/503_SERVICE_UNAVAILABLE.tsv
compiler/errors/template/class.txt
compiler/errors/template/sub_class.txt
tests/__init__.py
tests/test_file_id.py
tests/filters/__init__.py
tests/filters/test_command.py
zerogram/__init__.py
zerogram/client.py
zerogram/dispatcher.py
zerogram/emoji.py
zerogram/file_id.py
zerogram/filters.py
zerogram/mime_types.py
zerogram/py.typed
zerogram/sync.py
zerogram/syncer.py
zerogram/utils.py
zerogram.egg-info/PKG-INFO
zerogram.egg-info/SOURCES.txt
zerogram.egg-info/dependency_links.txt
zerogram.egg-info/not-zip-safe
zerogram.egg-info/requires.txt
zerogram.egg-info/top_level.txt
zerogram/connection/__init__.py
zerogram/connection/connection.py
zerogram/connection/transport/__init__.py
zerogram/connection/transport/tcp/__init__.py
zerogram/connection/transport/tcp/tcp.py
zerogram/connection/transport/tcp/tcp_abridged.py
zerogram/connection/transport/tcp/tcp_abridged_o.py
zerogram/connection/transport/tcp/tcp_full.py
zerogram/connection/transport/tcp/tcp_intermediate.py
zerogram/connection/transport/tcp/tcp_intermediate_o.py
zerogram/crypto/__init__.py
zerogram/crypto/aes.py
zerogram/crypto/mtproto.py
zerogram/crypto/prime.py
zerogram/crypto/rsa.py
zerogram/enums/__init__.py
zerogram/enums/auto_name.py
zerogram/enums/chat_action.py
zerogram/enums/chat_event_action.py
